ndindex/__init__.py
ndindex/_crt.py
ndindex/_slice.cpython-311-i386-linux-gnu.so
ndindex/_tuple.cpython-311-i386-linux-gnu.so
ndindex/_version.py
ndindex/array.py
ndindex/booleanarray.py
ndindex/chunking.py
ndindex/ellipsis.py
ndindex/integer.py
ndindex/integerarray.py
ndindex/ndindex.py
ndindex/newaxis.py
ndindex/shapetools.py
ndindex/slice.py
ndindex/subindex_helpers.py
ndindex/tuple.py
ndindex/tests/__init__.py
ndindex/tests/doctest.py
ndindex/tests/helpers.py
ndindex/tests/test_array.py
ndindex/tests/test_as_subindex.py
ndindex/tests/test_booleanarray.py
ndindex/tests/test_broadcast_arrays.py
ndindex/tests/test_chunking.py
ndindex/tests/test_crt.py
ndindex/tests/test_ellipsis.py
ndindex/tests/test_expand.py
ndindex/tests/test_integer.py
ndindex/tests/test_integerarray.py
ndindex/tests/test_isvalid.py
ndindex/tests/test_ndindex.py
ndindex/tests/test_newaxis.py
ndindex/tests/test_newshape.py
ndindex/tests/test_no_dependencies.py
ndindex/tests/test_selected_indices.py
ndindex/tests/test_shapetools.py
ndindex/tests/test_slice.py
ndindex/tests/test_tuple.py
ndindex-1.10.0.dist-info/METADATA
ndindex-1.10.0.dist-info/WHEEL
ndindex-1.10.0.dist-info/top_level.txt
ndindex-1.10.0.dist-info/RECORD
ndindex-1.10.0.dist-info/licenses/LICENSE
