Metadata-Version: 2.4
Name: ndindex
Version: 1.10.0
Summary: A Python library for manipulating indices of ndarrays.
Home-page: https://quansight-labs.github.io/ndindex/
Author: Quansight Labs
License: MIT
Classifier: Programming Language :: Python :: 3
Classifier: Operating System :: OS Independent
Requires-Python: >=3.9
License-File: LICENSE
Provides-Extra: arrays
Requires-Dist: numpy; extra == "arrays"
Dynamic: author
Dynamic: classifier
Dynamic: description
Dynamic: description-content-type
Dynamic: home-page
Dynamic: license
Dynamic: license-file
Dynamic: provides-extra
Dynamic: requires-python
Dynamic: summary
